Metadata-Version: 1.2
Name: botany-client
Version: 0.9.3
Summary: Botany client
Home-page: http://github.com/inglesp/botany
Author: Peter Inglesby
Author-email: peter.inglesby@gmail.com
License: License :: OSI Approved :: MIT License
Platform: UNKNOWN
Requires-Python: >=3.5
